{
    "commits": {
        "before": {
            "committer_date": "2025-05-26 03:39:11",
            "commit_id": "062387fb536",
            "message": "[SymmMem] Speed up tests (#153677)"
        },
        "after": {
            "committer_date": "2025-05-26 04:17:56",
            "commit_id": "7d11c61c26c",
            "message": "Re-enable FakeTensor caching for SymInts (#152662)"
        }
    },
    "completenessScore": [0.368078, 0.368016],
    "filename": "full-run/pyright_compare.083188.062387fb536-7d11c61c26c.json",
    "diff": {
        "absolute": {
            "exportedSymbolCounts": {"withKnownType": -1, "withUnknownType": 1},
            "completenessScore": -6.200781298443259e-05
        },
        "percent": {
            "exportedSymbolCounts": {
                "withKnownType": -0.016846361185983826,
                "withUnknownType": 0.010675776662752216
            },
            "completenessScore": -0.01684636118598289
        },
        "symbols": {
            "common": {
                "torch.fx.experimental.symbolic_shapes.ShapeEnv.evaluate_expr": {
                    "diagnostics": {
                        "added": [
                            "Type of parameter \"fx_node\" is partially unknown\n\u00a0\u00a0Parameter type is \"Node | None\""
                        ]
                    }
                }
            }
        }
    }
}
