{
    "commits": {
        "before": {
            "committer_date": "2025-07-25 21:17:06",
            "id": "24b1f10ca13",
            "message": "[HOP, map] Rework of map autograd to the new interface (#153343)"
        },
        "after": {
            "committer_date": "2025-07-25 21:19:49",
            "id": "7ef3c3357d8",
            "message": "NUMA binding integration with elastic agent and torchrun (#149334)"
        }
    },
    "completenessScore": [0.376655, 0.377298],
    "filename": "full-run/pyright_compare.085938.24b1f10ca13-7ef3c3357d8.json",
    "diff": {
        "absolute": {
            "exportedSymbolCounts": {
                "withKnownType": 18,
                "withAmbiguousType": 1,
                "withUnknownType": 1
            },
            "missingClassDocStringCount": 1,
            "completenessScore": 0.0006436025839182125,
            "filesAnalyzed": 2
        },
        "percent": {
            "exportedSymbolCounts": {
                "withKnownType": 0.2942137953579601,
                "withAmbiguousType": 0.11961722488038277,
                "withUnknownType": 0.010765421466250404
            },
            "missingClassDocStringCount": 0.09259259259259259,
            "completenessScore": 0.17087343528250284,
            "filesAnalyzed": 0.2290950744558992
        },
        "symbols": {
            "added": [
                "torch.distributed.elastic.agent.server.api.WorkerSpec.numa_options",
                "torch.distributed.launcher.api.LaunchConfig.numa_options",
                "torch.distributed.numa.binding.AffinityMode",
                "torch.distributed.numa.binding.AffinityMode.CORE_COMPLEX",
                "torch.distributed.numa.binding.AffinityMode.EXCLUSIVE",
                "torch.distributed.numa.binding.AffinityMode.NODE",
                "torch.distributed.numa.binding.AffinityMode.SOCKET",
                "torch.distributed.numa.binding.K",
                "torch.distributed.numa.binding.NumaOptions",
                "torch.distributed.numa.binding.NumaOptions.__dataclass_fields__",
                "torch.distributed.numa.binding.NumaOptions.__eq__",
                "torch.distributed.numa.binding.NumaOptions.__hash__",
                "torch.distributed.numa.binding.NumaOptions.__init__",
                "torch.distributed.numa.binding.NumaOptions.__match_args__",
                "torch.distributed.numa.binding.NumaOptions.__new__",
                "torch.distributed.numa.binding.NumaOptions.affinity_mode",
                "torch.distributed.numa.binding.NumaOptions.should_fall_back_if_binding_fails",
                "torch.distributed.numa.binding.V",
                "torch.distributed.numa.binding.logger",
                "torch.distributed.numa.binding.maybe_wrap_with_numa_bindings"
            ]
        }
    }
}
